asyncactor/__init__.py
asyncactor/abc.py
asyncactor/actor.py
asyncactor/events.py
asyncactor/exceptions.py
asyncactor/messages.py
asyncactor/nodelist.py
asyncactor/backend/__init__.py
asyncactor/backend/moat_kv.py
asyncactor/backend/moat_link.py
asyncactor/backend/mqtt.py
asyncactor/backend/mqttproto.py
asyncactor/backend/serf.py
asyncactor-0.28.2.dist-info/licenses/LICENSE
asyncactor-0.28.2.dist-info/METADATA
asyncactor-0.28.2.dist-info/WHEEL
asyncactor-0.28.2.dist-info/top_level.txt
asyncactor-0.28.2.dist-info/RECORD
