Metadata-Version: 2.4
Name: asyncactor
Version: 0.28.2
Summary: Async decentralized actor
Author-email: Matthias Urlichs <matthias@urlichs.de>
Project-URL: homepage, https://github.com/smurfix/asyncactor
Project-URL: repository, https://github.com/smurfix/asyncactor.git
Keywords: MQTT,orchestration,service discovery,anyio
Classifier: Intended Audience :: Developers
Classifier: Programming Language :: Python :: 3
Classifier: Framework :: AsyncIO
Classifier: Framework :: Trio
Classifier: Framework :: AnyIO
Classifier: License :: OSI Approved
Classifier: Development Status :: 4 - Beta
Requires-Python: >=3.9
License-File: LICENSE
Requires-Dist: anyio~=4.2
Requires-Dist: moat-lib-codec
Requires-Dist: moat-util~=0.53
Provides-Extra: moat-kv
Requires-Dist: moat-kv; extra == "moat-kv"
Provides-Extra: moat-link
Requires-Dist: moat-link; extra == "moat-link"
Provides-Extra: mqtt
Requires-Dist: moat-lib-mqtt; extra == "mqtt"
Provides-Extra: dev
Requires-Dist: moat-lib-mqtt; extra == "dev"
Requires-Dist: moat-mqtt; extra == "dev"
Requires-Dist: pytest-cov>=2.3; extra == "dev"
Requires-Dist: pytest-trio; extra == "dev"
Requires-Dist: pytest>=2.5.2; extra == "dev"
Requires-Dist: trio>=0.23; extra == "dev"
Dynamic: license-file
